pproject.py
pproject-0.0.8.dist-info/METADATA
pproject-0.0.8.dist-info/WHEEL
pproject-0.0.8.dist-info/entry_points.txt
pproject-0.0.8.dist-info/top_level.txt
pproject-0.0.8.dist-info/RECORD
