Metadata-Version: 2.1
Name: pproject
Version: 0.0.8
Summary: Predicted price change for iphone in XX years
Home-page: https://github.com/Sojiro4/pproject
Author: Sojiro4
Author-email: s2122097@stu.musashino-u.ac.jp
Project-URL: Bug Tracker, https://github.com/Sojiro4/pproject
Classifier: Programming Language :: Python :: 3
Classifier: License :: OSI Approved :: MIT License
Classifier: Operating System :: OS Independent
Requires-Python: >=3.11.3
